coverage_lcov/__init__.py
coverage_lcov/__main__.py
coverage_lcov/cli.py
coverage_lcov/converter.py
coverage_lcov-0.2.5.dist-info/entry_points.txt
coverage_lcov-0.2.5.dist-info/LICENSE
coverage_lcov-0.2.5.dist-info/WHEEL
coverage_lcov-0.2.5.dist-info/METADATA
coverage_lcov-0.2.5.dist-info/RECORD
