Metadata-Version: 2.1
Name: coverage-lcov
Version: 0.2.5
Summary: A simple .coverage to LCOV converter
Home-page: https://github.com/TheCleric/coverage-lcov
Keywords: coverage
Author: Adam Weeden
Author-email: adamweeden@gmail.com
Requires-Python: >=3.6.3,<4.0.0
Classifier: Programming Language :: Python :: 3
Classifier: Programming Language :: Python :: 3.10
Classifier: Programming Language :: Python :: 3.7
Classifier: Programming Language :: Python :: 3.8
Classifier: Programming Language :: Python :: 3.9
Requires-Dist: click (>=7.1.2)
Requires-Dist: coverage[toml] (>=5.5)
Requires-Dist: types-toml (>=0.1.5,<0.2.0)
Project-URL: Repository, https://github.com/TheCleric/coverage-lcov
